[{"id":"classic","label":"Classique","root":{"type":"Selector","name":"Root","children":[{"type":"Sequence","name":"Danger→Evade","children":[{"type":"Condition","ref":"danger","label":"Danger?"},{"type":"Action","ref":"evade","label":"Evade"}]},{"type":"Sequence","name":"Ranged→Attack","children":[{"type":"Condition","ref":"inRange","label":"InRanged?"},{"type":"Action","ref":"rangedAttack","label":"RangedAttack"}]},{"type":"Sequence","name":"Repositioning","children":[{"type":"Condition","ref":"needReposition","label":"NeedReposition?"},{"type":"Action","ref":"reposition","label":"Reposition"}]},{"type":"Action","ref":"patrol","label":"Patrol"}]}},{"id":"simple","label":"Simple","root":{"type":"Selector","name":"Root","children":[{"type":"Sequence","name":"Ranged→Attack","children":[{"type":"Condition","ref":"inRange","label":"InRanged?"},{"type":"Action","ref":"rangedAttack","label":"RangedAttack"}]},{"type":"Sequence","name":"Repositioning","children":[{"type":"Condition","ref":"needReposition","label":"NeedReposition?"},{"type":"Action","ref":"reposition","label":"Reposition"}]},{"type":"Action","ref":"patrol","label":"Patrol"}]}},{"id":"copy-0qpp0d","label":"Classique (copie)","root":{"type":"Selector","name":"Root","children":[{"type":"Sequence","name":"Danger→Evade","children":[{"type":"Condition","ref":"danger","label":"Danger?"},{"type":"Action","ref":"evade","label":"Evade"}]},{"type":"Sequence","name":"Ranged→Attack","children":[{"type":"Condition","ref":"inRange","label":"InRanged?"},{"type":"Action","ref":"rangedAttack","label":"RangedAttack"}]},{"type":"Sequence","name":"Repositioning","children":[{"type":"Condition","ref":"needReposition","label":"NeedReposition?"},{"type":"Action","ref":"reposition","label":"Reposition"}]},{"type":"Action","ref":"patrol","label":"Patrol"}]}},{"id":"copy-h4q0b5","label":"Classique (copie) (copie)","root":{"type":"Selector","name":"Root","children":[{"type":"Sequence","name":"Danger→Evade","children":[{"type":"Condition","ref":"danger","label":"Danger?"},{"type":"Action","ref":"evade","label":"Evade"}]},{"type":"Sequence","name":"Ranged→Attack","children":[{"type":"Condition","ref":"inRange","label":"InRanged?"},{"type":"Action","ref":"rangedAttack","label":"RangedAttack"}]},{"type":"Sequence","name":"Repositioning","children":[{"type":"Condition","ref":"needReposition","label":"NeedReposition?"},{"type":"Action","ref":"reposition","label":"Reposition"}]},{"type":"Action","ref":"patrol","label":"Patrol"}]}},{"id":"copy-0yckwl","label":"Classique (copie) (copie) (copie)","root":{"type":"Selector","name":"Root","children":[{"type":"Sequence","name":"Danger→Evade","children":[{"type":"Condition","ref":"danger","label":"Danger?"},{"type":"Action","ref":"evade","label":"Evade"}]},{"type":"Sequence","name":"Ranged→Attack","children":[{"type":"Condition","ref":"inRange","label":"InRanged?"},{"type":"Action","ref":"rangedAttack","label":"RangedAttack"}]},{"type":"Sequence","name":"Repositioning","children":[{"type":"Condition","ref":"needReposition","label":"NeedReposition?"},{"type":"Action","ref":"reposition","label":"Reposition"}]},{"type":"Action","ref":"patrol","label":"Patrol"}]}},{"id":"copy-9aj48o","label":"Classique (copie) (copie) (copie) (copie)","root":{"type":"Selector","name":"Root","children":[{"type":"Sequence","name":"Danger→Evade","children":[{"type":"Condition","ref":"danger","label":"Danger?"},{"type":"Action","ref":"evade","label":"Evade"}]},{"type":"Sequence","name":"Ranged→Attack","children":[{"type":"Condition","ref":"inRange","label":"InRanged?"},{"type":"Action","ref":"rangedAttack","label":"RangedAttack"}]},{"type":"Sequence","name":"Repositioning","children":[{"type":"Condition","ref":"needReposition","label":"NeedReposition?"},{"type":"Action","ref":"reposition","label":"Reposition"}]},{"type":"Action","ref":"patrol","label":"Patrol"}]}},{"id":"copy-n5qyou","label":"Classique (copie) (copie) (copie) (copie) (copie)","root":{"type":"Selector","name":"Root","children":[{"type":"Sequence","name":"Danger→Evade","children":[{"type":"Condition","ref":"danger","label":"Danger?"},{"type":"Action","ref":"evade","label":"Evade"}]},{"type":"Sequence","name":"Ranged→Attack","children":[{"type":"Condition","ref":"inRange","label":"InRanged?"},{"type":"Action","ref":"rangedAttack","label":"RangedAttack"}]},{"type":"Sequence","name":"Repositioning","children":[{"type":"Condition","ref":"needReposition","label":"NeedReposition?"},{"type":"Action","ref":"reposition","label":"Reposition"}]},{"type":"Action","ref":"patrol","label":"Patrol"}]}},{"id":"copy-haaxk7","label":"Classique (copie) (copie) (copie) (copie) (copie) (copie)","root":{"type":"Selector","name":"Root","children":[{"type":"Sequence","name":"Danger→Evade","children":[{"type":"Condition","ref":"danger","label":"Danger?"},{"type":"Action","ref":"evade","label":"Evade"}]},{"type":"Sequence","name":"Ranged→Attack","children":[{"type":"Condition","ref":"inRange","label":"InRanged?"},{"type":"Action","ref":"rangedAttack","label":"RangedAttack"}]},{"type":"Sequence","name":"Repositioning","children":[{"type":"Condition","ref":"needReposition","label":"NeedReposition?"},{"type":"Action","ref":"reposition","label":"Reposition"}]},{"type":"Action","ref":"patrol","label":"Patrol"}]}},{"id":"copy-73bjzs","label":"Classique (copie) (copie) (copie) (copie) (copie) (copie) (copie)","root":{"type":"Selector","name":"Root","children":[{"type":"Sequence","name":"Danger→Evade","children":[{"type":"Condition","ref":"danger","label":"Danger?"},{"type":"Action","ref":"evade","label":"Evade"}]},{"type":"Sequence","name":"Ranged→Attack","children":[{"type":"Condition","ref":"inRange","label":"InRanged?"},{"type":"Action","ref":"rangedAttack","label":"RangedAttack"}]},{"type":"Sequence","name":"Repositioning","children":[{"type":"Condition","ref":"needReposition","label":"NeedReposition?"},{"type":"Action","ref":"reposition","label":"Reposition"}]},{"type":"Action","ref":"patrol","label":"Patrol"}]}},{"id":"copy-voavce","label":"Classique (copie) (copie) (copie) (copie) (copie) (copie) (copie) (copie)","root":{"type":"Selector","name":"Root","children":[{"type":"Sequence","name":"Danger→Evade","children":[{"type":"Condition","ref":"danger","label":"Danger?"},{"type":"Action","ref":"evade","label":"Evade"}]},{"type":"Sequence","name":"Ranged→Attack","children":[{"type":"Condition","ref":"inRange","label":"InRanged?"},{"type":"Action","ref":"rangedAttack","label":"RangedAttack"}]},{"type":"Sequence","name":"Repositioning","children":[{"type":"Condition","ref":"needReposition","label":"NeedReposition?"},{"type":"Action","ref":"reposition","label":"Reposition"}]},{"type":"Action","ref":"patrol","label":"Patrol"}]}},{"id":"copy-17m8sq","label":"Classique (copie)","root":{"type":"Selector","name":"Root","children":[{"type":"Condition","ref":"danger","label":"Danger?"},{"type":"Sequence","name":"Danger→Evade","children":[{"type":"Action","ref":"evade","label":"Evade"}]},{"type":"Sequence","name":"Ranged→Attack","children":[{"type":"Condition","ref":"inRange","label":"InRanged?"},{"type":"Action","ref":"rangedAttack","label":"RangedAttack"}]},{"type":"Sequence","name":"Repositioning","children":[{"type":"Condition","ref":"needReposition","label":"NeedReposition?"},{"type":"Action","ref":"reposition","label":"Reposition"}]},{"type":"Action","ref":"patrol","label":"Patrol"}]}},{"id":"copy-p1x8br","label":"Classique (copie) (copie)","root":{"type":"Selector","name":"Root","children":[{"type":"Condition","ref":"danger","label":"Danger?"},{"type":"Sequence","name":"Danger→Evade","children":[{"type":"Action","ref":"evade","label":"Evade"}]},{"type":"Sequence","name":"Ranged→Attack","children":[{"type":"Condition","ref":"inRange","label":"InRanged?"},{"type":"Action","ref":"rangedAttack","label":"RangedAttack"}]},{"type":"Sequence","name":"Repositioning","children":[{"type":"Condition","ref":"needReposition","label":"NeedReposition?"},{"type":"Action","ref":"reposition","label":"Reposition"}]},{"type":"Action","ref":"patrol","label":"Patrol"}]}},{"id":"copy-0epznv","label":"Classique (copie) (copie) (copie)","root":{"type":"Selector","name":"Root","children":[{"type":"Condition","ref":"danger","label":"Danger?"},{"type":"Sequence","name":"Danger→Evade","children":[{"type":"Action","ref":"evade","label":"Evade"}]},{"type":"Sequence","name":"Ranged→Attack","children":[{"type":"Condition","ref":"inRange","label":"InRanged?"},{"type":"Action","ref":"rangedAttack","label":"RangedAttack"}]},{"type":"Sequence","name":"Repositioning","children":[{"type":"Condition","ref":"needReposition","label":"NeedReposition?"},{"type":"Action","ref":"reposition","label":"Reposition"}]},{"type":"Action","ref":"patrol","label":"Patrol"}]}},{"id":"copy-7tvyqz","label":"Classique (copie) (copie) (copie) (copie)","root":{"type":"Selector","name":"Root","children":[{"type":"Condition","ref":"danger","label":"Danger?"},{"type":"Sequence","name":"Danger→Evade","children":[{"type":"Action","ref":"evade","label":"Evade"}]},{"type":"Sequence","name":"Ranged→Attack","children":[{"type":"Condition","ref":"inRange","label":"InRanged?"},{"type":"Action","ref":"rangedAttack","label":"RangedAttack"}]},{"type":"Sequence","name":"Repositioning","children":[{"type":"Condition","ref":"needReposition","label":"NeedReposition?"},{"type":"Action","ref":"reposition","label":"Reposition"}]},{"type":"Action","ref":"patrol","label":"Patrol"}]}},{"id":"copy-rqmkwq","label":"Classique (copie) (copie) (copie) (copie) (copie)","root":{"type":"Selector","name":"Root","children":[{"type":"Condition","ref":"danger","label":"Danger?"},{"type":"Sequence","name":"Danger→Evade","children":[{"type":"Action","ref":"evade","label":"Evade"}]},{"type":"Sequence","name":"Ranged→Attack","children":[{"type":"Condition","ref":"inRange","label":"InRanged?"},{"type":"Action","ref":"rangedAttack","label":"RangedAttack"}]},{"type":"Sequence","name":"Repositioning","children":[{"type":"Condition","ref":"needReposition","label":"NeedReposition?"},{"type":"Action","ref":"reposition","label":"Reposition"}]},{"type":"Action","ref":"patrol","label":"Patrol"}]}}]